pyfakefs/__init__.py
pyfakefs/_version.py
pyfakefs/fake_file.py
pyfakefs/fake_filesystem.py
pyfakefs/fake_filesystem_shutil.py
pyfakefs/fake_filesystem_unittest.py
pyfakefs/fake_io.py
pyfakefs/fake_open.py
pyfakefs/fake_os.py
pyfakefs/fake_path.py
pyfakefs/fake_pathlib.py
pyfakefs/fake_scandir.py
pyfakefs/helpers.py
pyfakefs/mox3_stubout.py
pyfakefs/patched_packages.py
pyfakefs/py.typed
pyfakefs/pytest_plugin.py
pyfakefs/pytest_tests/__init__.py
pyfakefs/pytest_tests/conftest.py
pyfakefs/pytest_tests/example.py
pyfakefs/pytest_tests/fake_fcntl_test.py
pyfakefs/pytest_tests/io.py
pyfakefs/pytest_tests/lib_using_pathlib.py
pyfakefs/pytest_tests/local_import.py
pyfakefs/pytest_tests/pytest_check_failed_plugin_test.py
pyfakefs/pytest_tests/pytest_doctest_test.py
pyfakefs/pytest_tests/pytest_fixture_param_test.py
pyfakefs/pytest_tests/pytest_fixture_test.py
pyfakefs/pytest_tests/pytest_module_fixture_test.py
pyfakefs/pytest_tests/pytest_path_hint_test.py
pyfakefs/pytest_tests/pytest_plugin_failing_helper.py
pyfakefs/pytest_tests/pytest_plugin_test.py
pyfakefs/pytest_tests/pytest_reload_pandas_test.py
pyfakefs/pytest_tests/test_fs_with_monkeypatch.py
pyfakefs/pytest_tests/test_patch_on_setup.py
pyfakefs/pytest_tests/test_reload_local_import.py
pyfakefs/pytest_tests/unhashable.py
pyfakefs/pytest_tests/data/test.parquet
pyfakefs/pytest_tests/hook_test/conftest.py
pyfakefs/pytest_tests/hook_test/pytest_hook_test.py
pyfakefs/pytest_tests/ns_package/test/setup.py
pyfakefs/pytest_tests/ns_package/test/ns_package/test/test_file.py
pyfakefs/tests/__init__.py
pyfakefs/tests/all_tests.py
pyfakefs/tests/dynamic_patch_test.py
pyfakefs/tests/example.py
pyfakefs/tests/example_test.py
pyfakefs/tests/fake_filesystem_glob_test.py
pyfakefs/tests/fake_filesystem_shutil_test.py
pyfakefs/tests/fake_filesystem_test.py
pyfakefs/tests/fake_filesystem_unittest_test.py
pyfakefs/tests/fake_filesystem_vs_real_test.py
pyfakefs/tests/fake_open_test.py
pyfakefs/tests/fake_os_test.py
pyfakefs-6.0.0.dist-info/licenses/COPYING
pyfakefs-6.0.0.dist-info/METADATA
pyfakefs-6.0.0.dist-info/WHEEL
pyfakefs-6.0.0.dist-info/entry_points.txt
pyfakefs-6.0.0.dist-info/top_level.txt
pyfakefs-6.0.0.dist-info/RECORD
