Metadata-Version: 2.4
Name: pyfakefs
Version: 6.0.0
Summary: Implements a fake file system that mocks the Python file system modules.
Author-email: Google <google-pyfakefs@google.com>, John McGehee <pyfakefs@johnnado.com>
Maintainer-email: mrbean-bremen <hansemrbean@googlemail.com>
License-Expression: Apache-2.0
Project-URL: documentation, https://pytest-pyfakefs.readthedocs.io/
Project-URL: homepage, https://github.com/pytest-dev/pyfakefs
Project-URL: repository, https://github.com/pytest-dev/pyfakefs
Project-URL: changelog, https://github.com/pytest-dev/pyfakefs/blob/main/CHANGES.md
Keywords: testing,filesystem,mocking,unittest,pytest
Classifier: Development Status :: 5 - Production/Stable
Classifier: Environment :: Console
Classifier: Intended Audience :: Developers
Classifier: Programming Language :: Python :: 3
Classifier: Programming Language :: Python :: 3.10
Classifier: Programming Language :: Python :: 3.11
Classifier: Programming Language :: Python :: 3.12
Classifier: Programming Language :: Python :: 3.13
Classifier: Programming Language :: Python :: 3.14
Classifier: Programming Language :: Python :: Implementation :: CPython
Classifier: Programming Language :: Python :: Implementation :: PyPy
Classifier: Operating System :: POSIX
Classifier: Operating System :: MacOS
Classifier: Operating System :: Microsoft :: Windows
Classifier: Topic :: Software Development :: Libraries
Classifier: Topic :: Software Development :: Libraries :: Python Modules
Classifier: Topic :: Software Development :: Testing
Classifier: Topic :: System :: Filesystems
Classifier: Framework :: Pytest
Requires-Python: >=3.10
License-File: COPYING
Dynamic: license-file
